README.rst
setup.py
tests/__init__.py
tests/test_backends.py
tests/test_scipts.py
tests/test_verification_suit.py
tests/test_verificators.py
webapp_health_monitor/__init__.py
webapp_health_monitor/actions.py
webapp_health_monitor/errors.py
webapp_health_monitor/models.py
webapp_health_monitor/scripts.py
webapp_health_monitor/verification_suit.py
webapp_health_monitor/verificators_set.py
webapp_health_monitor.egg-info/PKG-INFO
webapp_health_monitor.egg-info/SOURCES.txt
webapp_health_monitor.egg-info/dependency_links.txt
webapp_health_monitor.egg-info/entry_points.txt
webapp_health_monitor.egg-info/not-zip-safe
webapp_health_monitor.egg-info/top_level.txt
webapp_health_monitor/backends/__init__.py
webapp_health_monitor/backends/system.py
webapp_health_monitor/management/__init__.py
webapp_health_monitor/management/commands/__init__.py
webapp_health_monitor/management/commands/verify.py
webapp_health_monitor/verificators/__init__.py
webapp_health_monitor/verificators/base.py
webapp_health_monitor/verificators/system.py