Metadata-Version: 1.0
Name: webapp-health-monitor
Version: 0.1.6.1
Summary: UNKNOWN
Home-page: https://github.com/pozytywnie/webapp-health-monitor
Author: Tomasz Wysocki
Author-email: tomasz@pozytywnie.pl
License: MIT
Platform: UNKNOWN
